ubersmith/__init__.py
ubersmith/__version__.py
ubersmith/config.py
ubersmith/api/core.py
ubersmith/client/__init__.py
ubersmith/client/api.py
ubersmith/client/base.py
ubersmith/util/__init__.py
ubersmith/util/cleaners.py
ubersmith/util/exceptions.py
ubersmith/util/files.py
ubersmith/util/parse.py
ubersmith_api-1.0.2.dist-info/licenses/LICENSE
ubersmith_api-1.0.2.dist-info/METADATA
ubersmith_api-1.0.2.dist-info/WHEEL
ubersmith_api-1.0.2.dist-info/top_level.txt
ubersmith_api-1.0.2.dist-info/RECORD
