Metadata-Version: 2.4
Name: ubersmith-api
Version: 1.0.2
Summary: Version-specific Python 3 wrapper for the Ubersmith API
Author-email: Ben Nassif <bennassif@gmail.com>
License-Expression: MIT
Project-URL: homepage, https://github.com/bnassif/ubersmith-api
Project-URL: issues, https://github.com/bnassif/ubersmith-api/issues
Keywords: api,wrapper,ubersmith,client
Classifier: Intended Audience :: Developers
Classifier: Natural Language :: English
Classifier: Operating System :: OS Independent
Classifier: Programming Language :: Python :: 3
Classifier: Programming Language :: Python :: 3.8
Classifier: Programming Language :: Python :: 3.9
Classifier: Programming Language :: Python :: 3.10
Classifier: Programming Language :: Python :: 3.11
Classifier: Programming Language :: Python :: 3.12
Requires-Python: >=3.10
License-File: LICENSE
Requires-Dist: requests>=1.0.4
Requires-Dist: pydantic-settings>=2.1.0
Requires-Dist: pydantic>=2.5.2
Provides-Extra: build
Requires-Dist: jinja2; extra == "build"
Dynamic: license-file
